codebase_to_llm/main.py
codebase_to_llm/application/__init__.py
codebase_to_llm/application/ports.py
codebase_to_llm/application/uc_add_code_snippet_to_context_buffer.py
codebase_to_llm/application/uc_add_external_source.py
codebase_to_llm/application/uc_add_file_as_prompt_variable.py
codebase_to_llm/application/uc_add_file_to_context_buffer.py
codebase_to_llm/application/uc_add_path_recent_repository_loaded_list.py
codebase_to_llm/application/uc_add_prompt_from_file.py
codebase_to_llm/application/uc_copy_context.py
codebase_to_llm/application/uc_modify_prompt.py
codebase_to_llm/application/uc_remove_elmts_from_context_buffer.py
codebase_to_llm/application/uc_set_prompt_from_favorite.py
codebase_to_llm/domain/__init__.py
codebase_to_llm/domain/context_buffer.py
codebase_to_llm/domain/directory_tree.py
codebase_to_llm/domain/favorite_prompts.py
codebase_to_llm/domain/prompt.py
codebase_to_llm/domain/recent_repositories.py
codebase_to_llm/domain/result.py
codebase_to_llm/domain/rules.py
codebase_to_llm/domain/value_object.py
codebase_to_llm/infrastructure/__init__.py
codebase_to_llm/infrastructure/filesystem_directory_repository.py
codebase_to_llm/infrastructure/filesystem_favorite_prompts_repository.py
codebase_to_llm/infrastructure/filesystem_recent_repository.py
codebase_to_llm/infrastructure/filesystem_rules_repository.py
codebase_to_llm/infrastructure/in_memory_context_buffer_repository.py
codebase_to_llm/infrastructure/in_memory_prompt_repository.py
codebase_to_llm/infrastructure/qt_clipboard_service.py
codebase_to_llm/infrastructure/url_external_source_repository.py
codebase_to_llm/interface/__init__.py
codebase_to_llm/interface/context_buffer.py
codebase_to_llm/interface/file_preview.py
codebase_to_llm/interface/main_window.py
codebase_to_llm/interface/prompts_dialogs.py
codebase_to_llm/interface/rules_dialogs.py
codebase_to_llm-0.0.4.1.dist-info/METADATA
codebase_to_llm-0.0.4.1.dist-info/WHEEL
codebase_to_llm-0.0.4.1.dist-info/entry_points.txt
codebase_to_llm-0.0.4.1.dist-info/top_level.txt
codebase_to_llm-0.0.4.1.dist-info/RECORD
