Metadata-Version: 2.4
Name: codebase_to_llm
Version: 0.0.4.1
Project-URL: Homepage, https://github.com/kevinduigou/codebase-to-llm
Requires-Dist: pyside6-stubs>=6.7.3.0
Requires-Dist: PySide6>=6.6.0
Requires-Dist: typing-extensions>=4.14.0
Requires-Dist: mypy>=1.0
Requires-Dist: pygments>=2.19.1
Requires-Dist: youtube-transcript-api>=0.6.2
Requires-Dist: trafilatura>=2.0.0
